{
  "nested": {
    "nested": {
      "nested": {
        "nested": {
          "nested": {
            "nested": {
              "nested": {
                "nested": {
                  "nested": {
                    "nested": {
                      "nested": {
                        "nested": [
                          1,
                          {
                            "x": "y"
                          },
                          null
                        ]
                      }
                    }
                  }
                }
              }
            }
          }
        }
      }
    }
  }
}
